dora_pyorbbecksdk/__init__.py
dora_pyorbbecksdk/main.py
dora_pyorbbecksdk-0.4.1.dist-info/METADATA
dora_pyorbbecksdk-0.4.1.dist-info/WHEEL
dora_pyorbbecksdk-0.4.1.dist-info/entry_points.txt
dora_pyorbbecksdk-0.4.1.dist-info/top_level.txt
dora_pyorbbecksdk-0.4.1.dist-info/RECORD
