Metadata-Version: 2.4
Name: dora-pyorbbecksdk
Version: 0.4.1
Summary: Dora Node for capturing video with PyOrbbeck SDK
Author-email: Haixuan Xavier Tao <tao.xavier@outlook.com>, Xiang Yang <Ryu-Yang@qq.com>
License: MIT
Requires-Python: >=3.8
Requires-Dist: dora-rs>=0.3.9
Requires-Dist: numpy<2.0.0
Requires-Dist: opencv-python>=4.1.1
